{
  "Checked": false,
  "Description": "图片缓存",
  "FileUris": [],
  "App": true,
  "lastModified": 0,
  "Name": "微信 朋友圈",
  "Notice": 0,
  "PackName": "com.tencent.mm",
  "Paths": [
    "PUBLIC_DATA/com.tencent.mm/micromsg/",
    "PUBLIC_DATA/com.tencent.mm/weixin/",
    "PUBLIC_DATA/com.tencent.mm/micromsg/",
    "PRIVATE_DATA/com.tencent.mm/micromsg/"
  ],
  "Redirect_Avoid": false,
  "Regexes": [
    "^\\/(?:.+?\\/)(?>(?:micromsg|weixin)\\/)(?>[a-z0-9]{32}\\/)(?>s(?:n|f)s\\/)(?>.+)$"
  ],
  "Size": 0,
  "type": 0
}